htmp/__init__.py
htmp/comment.py
htmp/container.py
htmp/display.py
htmp/document.py
htmp/element.py
htmp/elementor.py
htmp/markdown.py
htmp/protocol.py
htmp/spec.py
htmp/data/elements.yaml
htmp-0.1.0.dist-info/METADATA
htmp-0.1.0.dist-info/WHEEL
htmp-0.1.0.dist-info/top_level.txt
htmp-0.1.0.dist-info/RECORD
