Metadata-Version: 2.2
Name: HTMP
Version: 0.1.0
Requires-Python: >=3.10
Requires-Dist: IPython
Requires-Dist: ProtocolMan<0.2,>=0.1
